{
  "code": {
    "iso-1": {
      "ch": "Suisse"
    },
    "iso-2": {
      "ch-vs": "Valais"
    }
  },
  "foot": {
    "part-1": "travaux",
    "part-2": "projets",
    "part-3": "réseaux",
    "part-4": "colophon"
  },
  "page": {
    "proof": {
      "contact": "contact",
      "imprint": "impressum"
    },
    "stall": {
      "activities": "activités",
      "principles": "principes"
    }
  },
  "site": {
    "build": "code source",
    "email": "courrier électronique",
    "motto": "conception internet, édition numérique, etc.",
    "owner": "propriétaire et éditeur du site"
  }
}
